pyrev
test
