Metadata-Version: 1.1
Name: pyrev
Version: 0.38
Summary: Another Re:VIEW (lint) tool
Home-page: https://github.com/dmiyakawa/pyrev
Author: Daisuke Miyakawa
Author-email: d.miyakawa@gmail.com
License: Apache License 2.0
Platform: UNKNOWN
Classifier: Environment :: Console
Classifier: Intended Audience :: Developers
Classifier: License :: OSI Approved :: Apache Software License
Classifier: Operating System :: OS Independent
Classifier: Programming Language :: Python :: 2.7
Classifier: Topic :: Text Processing :: Markup
